.coveragerc
.gitignore
.travis.yml
README.md
codecov.yml
setup.cfg
setup.py
tox.ini
gene_map/__init__.py
gene_map/gene_mapper.py
gene_map/main.py
gene_map/utils.py
gene_map.egg-info/PKG-INFO
gene_map.egg-info/SOURCES.txt
gene_map.egg-info/dependency_links.txt
gene_map.egg-info/entry_points.txt
gene_map.egg-info/requires.txt
gene_map.egg-info/top_level.txt
gene_map/tests/__init__.py
gene_map/tests/test_artificial_mapping.py
gene_map/tests/test_uniprot.py