Metadata-Version: 1.1
Name: gene-map
Version: 0.4.4
Summary: Map gene ids using UniProt.
Home-page: https://github.com/kpj/gene_map
Author: kpj
Author-email: kpjkpjkpjkpjkpjkpj@gmail.com
License: MIT
Keywords: uniprot genes mapping
Platform: UNKNOWN
Classifier: Development Status :: 3 - Alpha
Classifier: Intended Audience :: End Users/Desktop
Classifier: Topic :: Scientific/Engineering :: Bio-Informatics
Classifier: License :: OSI Approved :: MIT License
Classifier: Programming Language :: Python :: 3 :: Only
